odoo/addons/project_task_creation_description_notification/README.rst
odoo/addons/project_task_creation_description_notification/__init__.py
odoo/addons/project_task_creation_description_notification/__manifest__.py
odoo/addons/project_task_creation_description_notification/i18n/it.po
odoo/addons/project_task_creation_description_notification/i18n/project_task_creation_description_notification.pot
odoo/addons/project_task_creation_description_notification/models/__init__.py
odoo/addons/project_task_creation_description_notification/models/project_task.py
odoo/addons/project_task_creation_description_notification/readme/CONTRIBUTORS.rst
odoo/addons/project_task_creation_description_notification/readme/DESCRIPTION.rst
odoo/addons/project_task_creation_description_notification/static/description/icon.png
odoo/addons/project_task_creation_description_notification/static/description/index.html
odoo/addons/project_task_creation_description_notification/tests/__init__.py
odoo/addons/project_task_creation_description_notification/tests/test_project_task_description_notification.py
odoo_addon_project_task_creation_description_notification-16.0.1.0.0.4.dist-info/METADATA
odoo_addon_project_task_creation_description_notification-16.0.1.0.0.4.dist-info/WHEEL
odoo_addon_project_task_creation_description_notification-16.0.1.0.0.4.dist-info/top_level.txt
odoo_addon_project_task_creation_description_notification-16.0.1.0.0.4.dist-info/RECORD
